{
  "main": {
    "id": "921c4b571968935c",
    "type": "split",
    "children": [
      {
        "id": "54aac2d5a7c1c0a5",
        "type": "tabs",
        "children": [
          {
            "id": "3bba920e7203df12",
            "type": "leaf",
            "state": {
              "type": "markdown",
              "state": {
                "file": "public/Преступление и Наказание.md",
                "mode": "source",
                "source": false
              }
            }
          }
        ]
      }
    ],
    "direction": "vertical"
  },
  "left": {
    "id": "2ecaecc234ebdfad",
    "type": "split",
    "children": [
      {
        "id": "7b6065589c78b58b",
        "type": "tabs",
        "children": [
          {
            "id": "142721be5317b1f9",
            "type": "leaf",
            "state": {
              "type": "file-explorer",
              "state": {
                "sortOrder": "alphabetical"
              }
            }
          },
          {
            "id": "87bc2d46f2dd2f75",
            "type": "leaf",
            "state": {
              "type": "search",
              "state": {
                "query": "",
                "matchingCase": false,
                "explainSearch": false,
                "collapseAll": false,
                "extraContext": false,
                "sortOrder": "alphabetical"
              }
            }
          },
          {
            "id": "440d5cd35be1fef2",
            "type": "leaf",
            "state": {
              "type": "bookmarks",
              "state": {}
            }
          }
        ]
      }
    ],
    "direction": "horizontal",
    "width": 300
  },
  "right": {
    "id": "bb8125071c4ea35e",
    "type": "split",
    "children": [
      {
        "id": "07a139cbe1a36d79",
        "type": "tabs",
        "children": [
          {
            "id": "298f8314d1a20f14",
            "type": "leaf",
            "state": {
              "type": "backlink",
              "state": {
                "file": "public/Преступление и Наказание.md",
                "collapseAll": false,
                "extraContext": false,
                "sortOrder": "alphabetical",
                "showSearch": false,
                "searchQuery": "",
                "backlinkCollapsed": false,
                "unlinkedCollapsed": true
              }
            }
          },
          {
            "id": "bee879dd1e548ad4",
            "type": "leaf",
            "state": {
              "type": "outgoing-link",
              "state": {
                "file": "public/Преступление и Наказание.md",
                "linksCollapsed": false,
                "unlinkedCollapsed": true
              }
            }
          },
          {
            "id": "f16fb8ed71a3d2e5",
            "type": "leaf",
            "state": {
              "type": "tag",
              "state": {
                "sortOrder": "frequency",
                "useHierarchy": true
              }
            }
          },
          {
            "id": "09ee2ca8e1907bb3",
            "type": "leaf",
            "state": {
              "type": "outline",
              "state": {
                "file": "public/Преступление и Наказание.md"
              }
            }
          }
        ]
      }
    ],
    "direction": "horizontal",
    "width": 300,
    "collapsed": true
  },
  "left-ribbon": {
    "hiddenItems": {
      "switcher:Open quick switcher": false,
      "graph:Open graph view": false,
      "canvas:Create new canvas": false,
      "daily-notes:Open today's daily note": false,
      "templates:Insert template": false,
      "command-palette:Open command palette": false
    }
  },
  "active": "3bba920e7203df12",
  "lastOpenFiles": [
    "private/README.md",
    "README.md",
    "public/Преступление и Наказание.md",
    "private/mekmek",
    "garden.code-workspace"
  ]
}